syflow/__init__.py
syflow/_core.cpython-310-x86_64-linux-gnu.so
syflow-0.1.0.data/data/include/GLFW/glfw3.h
syflow-0.1.0.data/data/include/GLFW/glfw3native.h
syflow-0.1.0.data/data/lib64/libglfw3.a
syflow-0.1.0.data/data/lib64/cmake/glfw3/glfw3Config.cmake
syflow-0.1.0.data/data/lib64/cmake/glfw3/glfw3ConfigVersion.cmake
syflow-0.1.0.data/data/lib64/cmake/glfw3/glfw3Targets-release.cmake
syflow-0.1.0.data/data/lib64/cmake/glfw3/glfw3Targets.cmake
syflow-0.1.0.data/data/lib64/pkgconfig/glfw3.pc
syflow-0.1.0.dist-info/METADATA
syflow-0.1.0.dist-info/WHEEL
syflow-0.1.0.dist-info/top_level.txt
syflow-0.1.0.dist-info/RECORD
syflow.libs/libcudart-c64a25f3.so.12.3.101
syflow.libs/libuuid-6395f7d6.so.1.3.0
syflow.libs/libcuda-b1c54397.so.545.23.08
syflow.libs/libpcre2-8-516f4c9d.so.0.7.1
syflow.libs/libudev-6ca67360.so.1.6.11
syflow.libs/libblkid-b1e34c65.so.1.1.0
syflow.libs/libmount-02901b63.so.1.1.0
syflow.libs/libselinux-64a010fa.so.1
